laroux/__init__.py
laroux/laroux.py
laroux-0.1.1.dist-info/LICENSE
laroux-0.1.1.dist-info/METADATA
laroux-0.1.1.dist-info/WHEEL
laroux-0.1.1.dist-info/top_level.txt
laroux-0.1.1.dist-info/RECORD
