Metadata-Version: 2.1
Name: laroux
Version: 0.1.1
Summary: A small, simple LRU cache
Home-page: https://github.com/waellison/laroux
Author: William Ellison
Author-email: waellison@gmail.com
Project-URL: Bug Tracker, https://github.com/waellison/laroux/issues
Project-URL: Maintainer's Blog, https://waellison.blog
Classifier: Programming Language :: Python :: 3.9
Classifier: Programming Language :: Python :: 3.10
Classifier: Programming Language :: Python :: 3.11
Classifier: Development Status :: 3 - Alpha
Classifier: License :: OSI Approved :: GNU Affero General Public License v3
Classifier: Environment :: Plugins
Classifier: Operating System :: OS Independent
Classifier: Topic :: Software Development :: Libraries :: Python Modules
Requires-Python: >=3.9
License-File: LICENSE
